noms/__init__.py
noms/auth.py
noms/templates/index.html
noms_auth-2.3.dist-info/METADATA
noms_auth-2.3.dist-info/WHEEL
noms_auth-2.3.dist-info/top_level.txt
noms_auth-2.3.dist-info/RECORD
