Metadata-Version: 2.1
Name: noms-auth
Version: 2.3
Summary: A package that allows you to import a module to backup your members!
Author: asov
Author-email: asov <noemtdev@gmail.com>
Project-URL: Homepage, https://github.com/noemtdev/auth
Project-URL: Bug Tracker, https://github.com/noemtdev/auth/issues
Keywords: python,discord,backup,members
Classifier: Programming Language :: Python :: 3
Classifier: License :: OSI Approved :: MIT License
Classifier: Operating System :: OS Independent
Requires-Python: >=3.7
Requires-Dist: aiohttp
Requires-Dist: aiosqlite
Requires-Dist: py-cord
Requires-Dist: quart
